bigquery_fdw/__init__.py
bigquery_fdw/bqclient.py
bigquery_fdw/bqclient_test.py
bigquery_fdw/fdw.py
bigquery_fdw-2.1.2.dist-info/LICENSE
bigquery_fdw-2.1.2.dist-info/METADATA
bigquery_fdw-2.1.2.dist-info/WHEEL
bigquery_fdw-2.1.2.dist-info/entry_points.txt
bigquery_fdw-2.1.2.dist-info/top_level.txt
bigquery_fdw-2.1.2.dist-info/RECORD
