Metadata-Version: 2.1
Name: bigquery-fdw
Version: 2.1.2
Summary: BigQuery Foreign Data Wrapper for PostgreSQL
Home-page: https://github.com/gabfl/bigquery_fdw
Author: Gabriel Bordeaux
Author-email: pypi@gab.lc
License: MIT
Classifier: Topic :: Database
Classifier: Topic :: Database :: Database Engines/Servers
Classifier: License :: OSI Approved :: MIT License
Classifier: Operating System :: MacOS
Classifier: Operating System :: POSIX :: Linux
Classifier: Natural Language :: English
Classifier: Programming Language :: Python :: 3
Classifier: Programming Language :: Python
Classifier: Development Status :: 4 - Beta
License-File: LICENSE
Requires-Dist: google-cloud-bigquery (==3.11.2)
Requires-Dist: google-auth (==2.21.0)
Requires-Dist: google-auth-oauthlib (==1.0.0)
Requires-Dist: protobuf (==4.21.8)
Requires-Dist: grpcio (==1.50.0)
Requires-Dist: grpcio-status (==1.50.0)
